gait/__init__.py
gait/ai_commit.py
gait/ai_pr.py
gait/git_wrapper.py
gait/github_wrapper.py
gait/linear_client.py
gait/main.py
gait/utils.py
gait_tool-0.1.0.dist-info/LICENSE
gait_tool-0.1.0.dist-info/METADATA
gait_tool-0.1.0.dist-info/WHEEL
gait_tool-0.1.0.dist-info/entry_points.txt
gait_tool-0.1.0.dist-info/top_level.txt
gait_tool-0.1.0.dist-info/RECORD
