Metadata-Version: 2.1
Name: gait-tool
Version: 0.1.0
Summary: An AI enhanced git command line utility
Author: Empyrean Technologies Inc
License:                                  Apache License
Project-URL: Homepage, https://github.com/EmpyreanTechnologiesInc/gait.git
Requires-Python: >=3.7
License-File: LICENSE
Requires-Dist: openai>=1.0.0
Requires-Dist: python-dotenv>=0.19.0
Requires-Dist: pydantic>=2.0.0
Requires-Dist: gql>=3.5.0
Requires-Dist: requests>=2.31.0
Requires-Dist: requests-toolbelt>=1.0.0
Requires-Dist: urllib3<=1.26.15
